get_a_shell/__init__.py
get_a_shell/get_a_shell.py
get_a_shell-1.1.dist-info/LICENSE
get_a_shell-1.1.dist-info/METADATA
get_a_shell-1.1.dist-info/WHEEL
get_a_shell-1.1.dist-info/entry_points.txt
get_a_shell-1.1.dist-info/top_level.txt
get_a_shell-1.1.dist-info/RECORD
