Metadata-Version: 2.1
Name: get-a-shell
Version: 1.1
Summary: Get a shell code (bind/reverse) into different languages 
Home-page: https://github.com/EmilienPer/GetAShell
Author: Emilien Peretti
Author-email: code@emilienperetti.be
License: AGPLv3
Platform: UNKNOWN
